pyfu_usb/__init__.py
pyfu_usb/__main__.py
pyfu_usb/descriptor.py
pyfu_usb/dfu.py
pyfu_usb/dfuse.py
pyfu_usb/py.typed
pyfu_usb-2.0.2.dist-info/METADATA
pyfu_usb-2.0.2.dist-info/WHEEL
pyfu_usb-2.0.2.dist-info/entry_points.txt
pyfu_usb-2.0.2.dist-info/licenses/LICENSE
pyfu_usb-2.0.2.dist-info/RECORD
