Metadata-Version: 2.4
Name: pyfu-usb
Version: 2.0.2
Summary: Python USB firmware update library.
Author: Block, Inc.
License: MIT
License-File: LICENSE
Keywords: dfu-util,pydfu
Requires-Python: >=3.8
Requires-Dist: pyusb>=1.0.2
Requires-Dist: rich>=12.2
